PC_Adder.v
module PC_Adder(input [31:0] PC,
                input isBranch,
                input isJump,
                input reg 
                output reg [31:0] incrementedPC);

  
    always@(*)
    begin
    //going to add mux here for branching
    
        incrementedPC <= PC+4;  
        
        
        
    end

endmodule

ProgramCounter.v
module ProgramCounter(input clk,
                      input reset,
                      input [31:0] nextPC,
                      output reg [31:0] PC
                      );


    always@(posedge clk or posedge reset)
    begin

        if(reset)
        begin
            PC <= 0;
        end

        else
        begin
            PC <= nextPC;
        end
    end

endmodule

ProgramCounter_tb.v
`timescale 1ns/1ns
`include "ProgramCounter.v"
`include "PC_Adder.v"

module ProgramCounter_tb;

    reg [31:0] nextPC;
    reg clk;
    reg reset;

    wire [31:0] PC;

    ProgramCounter pc1(.clk(clk), .reset(reset), .nextPC(nextPC), .PC(PC));
    
    always #5 clk = ~clk;

    initial
    begin


        $dumpfile("ProgramCounter_tb.vcd");
        $dumpvars(0, ProgramCounter_tb);
        clk = 0;
        reset = 0;
        nextPC = 32'b0;

        reset = 1;
        #10;
        reset = 0;
        
        nextPC = 32'h00004;
        #10;
        nextPC = 32'h00008;

        #10;
        reset = 1;
        #10;
        reset = 0;

        nextPC = 32'h0000C;

        #100;

        $display("TEST COMPLETE");
        $finish;

    end
        
endmodule

ProgramCounter_tb.vcd
$date
	Mon Aug 19 21:38:20 2024
$end
$version
	Icarus Verilog
$end
$timescale
	1ns
$end
$scope module ProgramCounter_tb $end
$var wire 32 ! PC [31:0] $end
$var reg 1 " clk $end
$var reg 32 # nextPC [31:0] $end
$var reg 1 $ reset $end
$scope module pc1 $end
$var wire 1 " clk $end
$var wire 32 % nextPC [31:0] $end
$var wire 1 $ reset $end
$var reg 32 & PC [31:0] $end
$upscope $end
$upscope $end
$enddefinitions $end
$comment Show the parameter values. $end
$dumpall
$end
#0
$dumpvars
b0 &
b0 %
1$
b0 #
0"
b0 !
$end
#5
1"
#10
0"
b100 #
b100 %
0$
#15
b100 !
b100 &
1"
#20
0"
b1000 #
b1000 %
#25
b1000 !
b1000 &
1"
#30
b0 !
b0 &
0"
1$
#35
1"
#40
0"
b1100 #
b1100 %
0$
#45
b1100 !
b1100 &
1"
